<?xml version="1.0" encoding="UTF-8"?>
<odoo>
    <record id="edit_project_inherit_eram_inventory" model="ir.ui.view">
        <field name="name">project.project.form.inherit.eram.inventory</field>
        <field name="model">project.project</field>
        <field name="inherit_id" ref="project.edit_project"/>
        <field name="arch" type="xml">
            <xpath expr="//div[hasclass('oe_button_box')]" position="inside">
                <button class="oe_stat_button" type="object" name="action_view_outwards" icon="fa-solid fa-outdent">
                    <div class="o_field_widget o_stat_info">
                        <span class="o_stat_text">Outwards</span>
                    </div>
                </button>
            </xpath>
        </field>
    </record>
</odoo>